pyup/__init__.py
pyup/bot.py
pyup/cli.py
pyup/config.py
pyup/errors.py
pyup/package.py
pyup/pullrequest.py
pyup/requirements.py
pyup/settings.py
pyup/updates.py
pyup/providers/__init__.py
pyup/providers/github.py
pyup/providers/gitlab.py
pyup/templates/_api_key.md
pyup/templates/_bundled_updates.md
pyup/templates/_changelog.md
pyup/templates/initial_update_body.md
pyup/templates/scheduled_update_body.md
pyup/templates/sequential_update_body.md
pyupio-1.1.2.dist-info/AUTHORS.rst
pyupio-1.1.2.dist-info/LICENSE
pyupio-1.1.2.dist-info/METADATA
pyupio-1.1.2.dist-info/WHEEL
pyupio-1.1.2.dist-info/entry_points.txt
pyupio-1.1.2.dist-info/top_level.txt
pyupio-1.1.2.dist-info/RECORD
