Metadata-Version: 2.1
Name: pyupio
Version: 1.1.2
Summary: A tool to update all your projects requirements
Home-page: https://github.com/pyupio/pyup
Author: Jannis Gebauer
Author-email: support@pyup.io
License: MIT
Keywords: pyup
Platform: UNKNOWN
Classifier: Development Status :: 4 - Beta
Classifier: Intended Audience :: Developers
Classifier: License :: OSI Approved :: MIT License
Classifier: Natural Language :: English
Classifier: Programming Language :: Python
Classifier: Programming Language :: Python :: 3
Classifier: Programming Language :: Python :: 3.5
Classifier: Programming Language :: Python :: 3.6
Classifier: Programming Language :: Python :: 3.7
Classifier: Programming Language :: Python :: 3.8
Classifier: Programming Language :: Python :: Implementation :: CPython
Requires-Python: >=3.5
